LICENSE
sql_test_cli/cli/__init__.py
sql_test_cli/cli/commands.py
sql_test_cli/cli/outputs.py
sql_test_cli/core/__init__.py
sql_test_cli/core/config.py
sql_test_cli/core/config_manager.py
sql_test_cli/core/connection.py
sql_test_cli/core/directory_check.py
sql_test_cli/core/initialize.py
sql_test_cli/core/logger.py
sql_test_cli/core/run.py
sql_test_cli/core/run_test.py
sql_test_cli/core/utils.py
sql_test_cli-0.1.4.dist-info/LICENSE
sql_test_cli-0.1.4.dist-info/METADATA
sql_test_cli-0.1.4.dist-info/WHEEL
sql_test_cli-0.1.4.dist-info/entry_points.txt
sql_test_cli-0.1.4.dist-info/RECORD
