Metadata-Version: 2.1
Name: sql-test-cli
Version: 0.1.4
Summary: A CLI tool for executing sql tests.
License: MIT
Author: cohenj20
Author-email: cohenj20@sacredheart.edu
Requires-Python: >=3.10,<4.0
Classifier: License :: OSI Approved :: MIT License
Classifier: Programming Language :: Python :: 3
Classifier: Programming Language :: Python :: 3.10
Classifier: Programming Language :: Python :: 3.11
Classifier: Programming Language :: Python :: 3.12
Requires-Dist: click (>=8.1.7,<9.0.0)
Requires-Dist: colorama (>=0.4.6,<0.5.0)
Requires-Dist: pandas (>=2.2.1,<3.0.0)
Requires-Dist: pyodbc (>=5.1.0,<6.0.0)
Requires-Dist: pyyaml (>=6.0.1,<7.0.0)
Requires-Dist: sqlalchemy (==2.0.28)
